Workbook

Sheet Matrix
B1: KEY | C1: 1=Absent | D1: 2=Minimal | E1: 3=Basic | F1: 4=Strong | G1: 5=Best In Class
A3: Feature | B3: Bloomberg | C3: Robinhood | D3: Fidelity | E3: Investopedia Sim | F3: TradingView | G3: Ally Invest | H3: Empower | I3: Charles Schwab | J3: TD Bank | K3: T. Rowe Price | L3: Vanguard | M3: Webull | N3: Average Score | O3: Last Reviewed | P3: Notes
A4: Cost
A5: Monetiation Strategy | B5: Monthly Subsription | C5: Monthly Subsription | D5: Advisory Fee | E5: FREE | F5: Monthly Subsription | G5: Advisory Fee | H5: Not specified | I5: Various | J5: Flat Fee per contract | K5: Advisory Fee | L5: Per Trade | M5: Various | O5: 45996
A6: Lowest tier cost | B6: 2020 | C6: 0 | D6: Free | F6: 12.95 | G6: 0 | H6: 0 | I6: 0 | J6: 9.99 | K6: Various | L6: 0 | M6: Regulatory Fee based on volume | O6: 45996
A7: Middle tier cost | B7: - | C7: - | D7: 0.0035 | F7: 56.49 | G7: 0.003 | I7: Various | K7: Various | M7: - | O7: 46016
A8: highest tier cost | B8: =32000/12 -> 2666.6667 | C8: 5 | D8: 0.015 | F8: 199 | G8: 0.0085 | I8: 30 | J8: 7 | K8: Various | L8: 25 | M8: 3.99 | O8: 46016
A9: User Profile & Target Segment | B9: =SUM(B10:B13) -> 2.5 | C9: =SUM(C10:C13) -> 3.75 | D9: =SUM(D10:D13) -> 3.75 | E9: =SUM(E10:E13) -> 2.5 | F9: =SUM(F10:F13) -> 3.75 | G9: =SUM(G10:G13) -> 3.75 | H9: =SUM(H10:H13) -> 2.5 | I9: =SUM(I10:I13) -> 3.75 | ... M9: =SUM(M10:M13) -> 3.75 | P9: Special Scale, each target user profile gets 1.25 points.
A10: Retail beginner | B10: - | C10: 1.25 | D10: 1.25 | E10: 1.25 | F10: 1.25 | G10: 1.25 | H10: 1.25 | I10: 1.25 | J10: 1.25 | K10: 1.25 | L10: 1.25 | M10: 1.25 | O10: 45996
A11: Retail intermediate | B11: - | C11: 1.25 | D11: 1.25 | E11: 1.25 | F11: 1.25 | G11: 1.25 | H11: 1.25 | I11: 1.25 | J11: 1.25 | K11: 1.25 | L11: 1.25 | M11: 1.25 | O11: 45996
A12: Advanced / active trader | B12: 1.25 | C12: 1.25 | D12: 1.25 | E12: - | F12: 1.25 | G12: 1.25 | I12: 1.25 | J12: 1.25 | M12: 1.25 | O12: 45996
A13: Professional / institutional | B13: 1.25 | C13: - | D13: - | E13: - | F13: - | O13: 45996
A14: Learning, Training & Simulation | B14: =AVERAGE(B17:B21) -> 4 | C14: =AVERAGE(C17:C21) -> 2.8 | D14: =AVERAGE(D17:D21) -> 3.2 | E14: =AVERAGE(E17:E21) -> 3.2 | F14: =AVERAGE(F17:F21) -> 2.4 | G14: =AVERAGE(G17:G21) -> 3.2 | H14: =AVERAGE(H17:H21) -> 2.6 | I14: =AVERAGE(I17:I21) -> 3.8 | ... M14: =AVERAGE(M17:M21) -> 2.4 | N14: =AVERAGE(B14:M14) -> 2.95
A15: Finance 101 - Entry level learning content | B15: 1 | C15: 5 | D15: 5 | E15: 5 | F15: 1 | G15: 4 | H15: 3 | I15: 4 | J15: 1 | K15: 2 | L15: 3 | M15: 5 | N15: =AVERAGE(B15:M15) -> 3.25 | O15: 45996
A16: Advanced Training (Puts, Shorting, other adv methods) | B16: 1 | C16: 3 | D16: 3 | E16: 2 | F16: 1 | G16: 3 | H16: 1 | I16: 4 | J16: 1 | K16: 1 | L16: 2 | M16: 5 | N16: =AVERAGE(B16:M16) -> 2.25 | O16: 45996
A17: Paper trading Simulator? | B17: 4 | C17: 4 | D17: 3 | E17: 3 | F17: 2 | G17: 3 | H17: 3 | I17: 3 | J17: 3 | K17: 2 | L17: 3 | M17: 4 | N17: =AVERAGE(B17:M17) -> 3.0833333 | O17: 45996
A18: Tutorials | B18: 5 | C18: 2 | D18: 3 | E18: 3 | F18: 3 | G18: 3 | H18: 2 | I18: 3 | J18: 4 | K18: 2 | L18: 2 | M18: 2 | N18: =AVERAGE(B18:M18) -> 2.8333333 | O18: 45996
A19: Quizzes | B19: 5 | C19: 3 | D19: 3 | E19: 5 | F19: 1 | G19: 4 | H19: 3 | I19: 4 | J19: 1 | K19: 2 | L19: 2 | M19: 1 | N19: =AVERAGE(B19:M19) -> 2.8333333 | O19: 45996
A20: Software Training - how to use platform features | B20: 4 | C20: 3 | D20: 4 | E20: 3 | F20: 4 | G20: 3 | H20: 3 | I20: 4 | J20: 3 | K20: 3 | L20: 3 | M20: 3 | N20: =AVERAGE(B20:M20) -> 3.3333333 | O20: 45996
A21: Guided trade features | B21: 2 | C21: 2 | D21: 3 | E21: 2 | F21: 2 | G21: 3 | H21: 2 | I21: 5 | J21: 2 | K21: 3 | L21: 4 | M21: 2 | N21: =AVERAGE(B21:M21) -> 2.6666667 | O21: 45996
A22: Asset Classes Supported | B22: =AVERAGE(B23:B31) -> 3.6666667 | C22: =AVERAGE(C23:C31) -> 3.2222222 | D22: =AVERAGE(D23:D31) -> 3.5555556 | E22: =AVERAGE(E23:E31) -> 3.3333333 | F22: =AVERAGE(F23:F31) -> 3.1111111 | G22: =AVERAGE(G23:G31) -> 2.8888889 | H22: =AVERAGE(H23:H31) -> 3.6666667 | I22: =AVERAGE(I23:I31) -> 3.3333333 | ... M22: =AVERAGE(M23:M31) -> 2.7777778 | N22: =AVERAGE(B22:M22) -> 3.4166667 | P22: **The data in the rows below were AI generated and need to be verified
A23: Stocks | B23: 4 | C23: 3 | D23: 4 | E23: 2 | F23: 3 | G23: 2 | H23: 5 | I23: 4 | J23: 2 | K23: 3 | L23: 4 | M23: 3 | N23: =AVERAGE(B23:M23) -> 3.25 | P23: THIS ROW TEMPLATE ONLY
A24: ETFs | B24: 5 | C24: 5 | D24: 5 | E24: 3 | F24: 4 | G24: 3 | H24: 4 | I24: 5 | J24: 5 | K24: 4 | L24: 3 | M24: 3 | N24: =AVERAGE(B24:M24) -> 4.0833333 | P24: THIS ROW TEMPLATE ONLY
A25: Mutual funds | B25: 5 | C25: 2 | D25: 2 | E25: 2 | F25: 3 | G25: 3 | H25: 2 | I25: 5 | J25: 5 | K25: 5 | L25: 4 | M25: 2 | N25: =AVERAGE(B25:M25) -> 3.3333333 | P25: THIS ROW TEMPLATE ONLY
A26: Options | B26: 2 | C26: 4 | D26: 4 | E26: 2 | F26: 4 | G26: 5 | H26: 5 | I26: 2 | J26: 4 | K26: 3 | L26: 2 | M26: 4 | N26: =AVERAGE(B26:M26) -> 3.4166667 | P26: THIS ROW TEMPLATE ONLY
A27: Futures | B27: 3 | C27: 3 | D27: 4 | E27: 3 | F27: 2 | G27: 4 | H27: 2 | I27: 2 | J27: 4 | K27: 4 | L27: 3 | M27: 2 | N27: =AVERAGE(B27:M27) -> 3 | P27: THIS ROW TEMPLATE ONLY
A28: Forex | B28: 3 | C28: 2 | D28: 2 | E28: 5 | F28: 2 | G28: 3 | H28: 5 | I28: 3 | J28: 4 | K28: 5 | L28: 3 | M28: 3 | N28: =AVERAGE(B28:M28) -> 3.3333333 | P28: THIS ROW TEMPLATE ONLY
A29: Crypto | B29: 4 | C29: 5 | D29: 4 | E29: 5 | F29: 5 | G29: 2 | H29: 3 | I29: 2 | J29: 4 | K29: 2 | L29: 3 | M29: 3 | N29: =AVERAGE(B29:M29) -> 3.5 | P29: THIS ROW TEMPLATE ONLY
A30: Fixed income | B30: 2 | C30: 2 | D30: 2 | E30: 3 | F30: 2 | G30: 2 | H30: 2 | I30: 3 | J30: 4 | K30: 5 | L30: 3 | M30: 3 | N30: =AVERAGE(B30:M30) -> 2.75 | P30: THIS ROW TEMPLATE ONLY
A31: Alternatives (private equity, structured products) | B31: 5 | C31: 3 | D31: 5 | E31: 5 | F31: 3 | G31: 2 | H31: 5 | I31: 4 | J31: 5 | K31: 5 | L31: 5 | M31: 2 | N31: =AVERAGE(B31:M31) -> 4.0833333 | P31: THIS ROW TEMPLATE ONLY
A32: Account Types & Brokerage Functionality | B32: =AVERAGE(B33:B38) -> 3 | C32: =AVERAGE(C33:C38) -> 3.3333333 | D32: =AVERAGE(D33:D38) -> 3.3333333 | E32: =AVERAGE(E33:E38) -> 3.6666667 | F32: =AVERAGE(F33:F38) -> 2.8333333 | G32: =AVERAGE(G33:G38) -> 3.1666667 | H32: =AVERAGE(H33:H38) -> 2.5 | I32: =AVERAGE(I33:I38) -> 4.1666667 | ... M32: =AVERAGE(M33:M38) -> 3.6666667 | N32: =AVERAGE(B32:M32) -> 3.375 | P32: **The data in the rows below were AI generated and need to be verified
A33: Standard brokerage | B33: 2 | C33: 2 | D33: 5 | E33: 4 | F33: 2 | G33: 3 | H33: 3 | I33: 5 | J33: 3 | K33: 5 | L33: 3 | M33: 4 | N33: =AVERAGE(B33:M33) -> 3.4166667 | P33: THIS ROW TEMPLATE ONLY
A34: Retirement accounts (IRA, Roth) | B34: 5 | C34: 3 | D34: 2 | E34: 5 | F34: 2 | G34: 2 | H34: 2 | I34: 3 | J34: 3 | K34: 5 | L34: 5 | M34: 5 | N34: =AVERAGE(B34:M34) -> 3.5 | P34: THIS ROW TEMPLATE ONLY
A35: Margin accounts | B35: 3 | C35: 5 | D35: 2 | E35: 3 | F35: 5 | G35: 2 | H35: 4 | I35: 5 | J35: 4 | K35: 5 | L35: 5 | M35: 3 | N35: =AVERAGE(B35:M35) -> 3.8333333 | P35: THIS ROW TEMPLATE ONLY
A36: Custodial accounts | B36: 3 | C36: 4 | D36: 3 | E36: 2 | F36: 2 | G36: 4 | H36: 2 | I36: 5 | J36: 3 | K36: 2 | L36: 2 | M36: 3 | N36: =AVERAGE(B36:M36) -> 2.9166667 | P36: THIS ROW TEMPLATE ONLY
A37: Fractional shares | B37: 2 | C37: 2 | D37: 3 | E37: 5 | F37: 2 | G37: 3 | H37: 2 | I37: 5 | J37: 4 | K37: 4 | L37: 3 | M37: 4 | N37: =AVERAGE(B37:M37) -> 3.25 | P37: THIS ROW TEMPLATE ONLY
A38: Automated investing / robo-advisor | B38: 3 | C38: 4 | D38: 5 | E38: 3 | F38: 4 | G38: 5 | H38: 2 | I38: 2 | J38: 5 | K38: 2 | L38: 2 | M38: 3 | N38: =AVERAGE(B38:M38) -> 3.3333333 | P38: THIS ROW TEMPLATE ONLY
A39: Trading Tools | B39: =AVERAGE(B40:B46) -> 3.1428571 | C39: =AVERAGE(C40:C46) -> 2.8571429 | D39: =AVERAGE(D40:D46) -> 3.1428571 | E39: =AVERAGE(E40:E46) -> 2.8571429 | F39: =AVERAGE(F40:F46) -> 3.4285714 | G39: =AVERAGE(G40:G46) -> 3.5714286 | H39: =AVERAGE(H40:H46) -> 3.1428571 | I39: =AVERAGE(I40:I46) -> 3.5714286 | ... M39: =AVERAGE(M40:M46) -> 3.1428571 | N39: =AVERAGE(B39:M39) -> 3.3571429 | P39: **The data in the rows below were AI generated and need to be verified
A40: Order types | B40: 4 | C40: 3 | D40: 4 | E40: 2 | F40: 3 | G40: 4 | H40: 3 | I40: 5 | J40: 4 | K40: 2 | L40: 4 | M40: 2 | N40: =AVERAGE(B40:M40) -> 3.3333333 | P40: THIS ROW TEMPLATE ONLY
A41: Advanced order routing | B41: 3 | C41: 4 | D41: 2 | E41: 2 | F41: 3 | G41: 4 | H41: 3 | I41: 4 | J41: 3 | K41: 4 | L41: 5 | M41: 4 | N41: =AVERAGE(B41:M41) -> 3.4166667 | P41: THIS ROW TEMPLATE ONLY
A42: Real-time data | B42: 2 | C42: 2 | D42: 5 | E42: 4 | F42: 2 | G42: 2 | H42: 3 | I42: 4 | J42: 3 | K42: 5 | L42: 5 | M42: 2 | N42: =AVERAGE(B42:M42) -> 3.25 | P42: THIS ROW TEMPLATE ONLY
A43: Options analytics | B43: 2 | C43: 2 | D43: 3 | E43: 2 | F43: 4 | G43: 3 | H43: 3 | I43: 2 | J43: 4 | K43: 4 | L43: 2 | M43: 4 | N43: =AVERAGE(B43:M43) -> 2.9166667 | P43: THIS ROW TEMPLATE ONLY
A44: Screeners and scanners | B44: 3 | C44: 3 | D44: 2 | E44: 4 | F44: 5 | G44: 3 | H44: 3 | I44: 3 | J44: 5 | K44: 2 | L44: 3 | M44: 4 | N44: =AVERAGE(B44:M44) -> 3.3333333 | P44: THIS ROW TEMPLATE ONLY
A45: Backtesting tools | B45: 5 | C45: 3 | D45: 4 | E45: 3 | F45: 2 | G45: 5 | H45: 5 | I45: 3 | J45: 3 | K45: 5 | L45: 4 | M45: 4 | N45: =AVERAGE(B45:M45) -> 3.8333333 | P45: THIS ROW TEMPLATE ONLY
A46: API access | B46: 3 | C46: 3 | D46: 2 | E46: 3 | F46: 5 | G46: 4 | H46: 2 | I46: 4 | J46: 4 | K46: 5 | L46: 4 | M46: 2 | N46: =AVERAGE(B46:M46) -> 3.4166667 | P46: THIS ROW TEMPLATE ONLY
A47: Research & Analytics | B47: =AVERAGE(B48:B51) -> 3.25 | C47: =AVERAGE(C48:C51) -> 3.25 | D47: =AVERAGE(D48:D51) -> 4.25 | E47: =AVERAGE(E48:E51) -> 3.25 | F47: =AVERAGE(F48:F51) -> 2.75 | G47: =AVERAGE(G48:G51) -> 3 | H47: =AVERAGE(H48:H51) -> 3.25 | I47: =AVERAGE(I48:I51) -> 3.5 | ... M47: =AVERAGE(M48:M51) -> 4 | N47: =AVERAGE(B47:M47) -> 3.4791667 | P47: **The data in the rows below were AI generated and need to be verified
A48: Charting | B48: 2 | C48: 4 | D48: 3 | E48: 4 | F48: 2 | G48: 2 | H48: 4 | I48: 4 | J48: 5 | K48: 2 | L48: 5 | M48: 3 | N48: =AVERAGE(B48:M48) -> 3.3333333 | P48: THIS ROW TEMPLATE ONLY
A49: Technical indicators | B49: 4 | C49: 2 | D49: 5 | E49: 2 | F49: 3 | G49: 4 | H49: 2 | I49: 4 | J49: 4 | K49: 2 | L49: 4 | M49: 4 | N49: =AVERAGE(B49:M49) -> 3.3333333 | P49: THIS ROW TEMPLATE ONLY
A50: Fundamental data | B50: 5 | C50: 4 | D50: 5 | E50: 4 | F50: 3 | G50: 3 | H50: 5 | I50: 3 | J50: 4 | K50: 5 | L50: 2 | M50: 4 | N50: =AVERAGE(B50:M50) -> 3.9166667 | P50: THIS ROW TEMPLATE ONLY
A51: Analyst ratings | B51: 2 | C51: 3 | D51: 4 | E51: 3 | F51: 3 | G51: 3 | H51: 2 | I51: 3 | J51: 5 | K51: 2 | L51: 5 | M51: 5 | N51: =AVERAGE(B51:M51) -> 3.3333333 | P51: THIS ROW TEMPLATE ONLY
A52: Portfolio Management Tools | B52: =AVERAGE(B53:B57) -> 3 | C52: =AVERAGE(C53:C57) -> 3.6 | D52: =AVERAGE(D53:D57) -> 4.6 | E52: =AVERAGE(E53:E57) -> 3.6 | F52: =AVERAGE(F53:F57) -> 3.8 | G52: =AVERAGE(G53:G57) -> 4.4 | H52: =AVERAGE(H53:H57) -> 4.6 | I52: =AVERAGE(I53:I57) -> 4 | ... M52: =AVERAGE(M53:M57) -> 3.6 | N52: =AVERAGE(B52:M52) -> 3.9666667 | P52: **The data in the rows below were AI generated and need to be verified
A53: Performance tracking | B53: 3 | C53: 2 | D53: 5 | E53: 3 | F53: 5 | G53: 4 | H53: 5 | I53: 5 | J53: 3 | K53: 5 | L53: 5 | M53: 4 | N53: =AVERAGE(B53:M53) -> 4.0833333 | P53: THIS ROW TEMPLATE ONLY
A54: Asset allocation | B54: 3 | C54: 4 | D54: 5 | E54: 3 | F54: 4 | G54: 5 | H54: 4 | I54: 3 | J54: 4 | K54: 4 | L54: 4 | M54: 2 | N54: =AVERAGE(B54:M54) -> 3.75 | P54: THIS ROW TEMPLATE ONLY
A55: Risk metrics | B55: 3 | C55: 3 | D55: 3 | E55: 5 | F55: 3 | G55: 3 | H55: 5 | I55: 5 | J55: 4 | K55: 5 | L55: 5 | M55: 2 | N55: =AVERAGE(B55:M55) -> 3.8333333 | P55: THIS ROW TEMPLATE ONLY
A56: Tax optimization | B56: 3 | C56: 5 | D56: 5 | E56: 2 | F56: 5 | G56: 5 | H56: 4 | I56: 4 | J56: 5 | K56: 5 | L56: 3 | M56: 5 | N56: =AVERAGE(B56:M56) -> 4.25 | P56: THIS ROW TEMPLATE ONLY
A57: External account aggregation | B57: 3 | C57: 4 | D57: 5 | E57: 5 | F57: 2 | G57: 5 | H57: 5 | I57: 3 | J57: 5 | K57: 3 | L57: 2 | M57: 5 | N57: =AVERAGE(B57:M57) -> 3.9166667 | P57: THIS ROW TEMPLATE ONLY
A58: User Experience & UI | B58: =AVERAGE(B59:B63) -> 4.2 | C58: =AVERAGE(C59:C63) -> 3.6 | D58: =AVERAGE(D59:D63) -> 2.8 | E58: =AVERAGE(E59:E63) -> 4.4 | F58: =AVERAGE(F59:F63) -> 3.6 | G58: =AVERAGE(G59:G63) -> 4 | H58: =AVERAGE(H59:H63) -> 4.2 | I58: =AVERAGE(I59:I63) -> 4 | ... M58: =AVERAGE(M59:M63) -> 4 | N58: =AVERAGE(B58:M58) -> 3.9166667 | P58: **The data in the rows below were AI generated and need to be verified
A59: Mobile app | B59: 4 | C59: 2 | D59: 2 | E59: 4 | F59: 5 | G59: 4 | H59: 4 | I59: 2 | J59: 5 | K59: 5 | L59: 2 | M59: 5 | N59: =AVERAGE(B59:M59) -> 3.6666667 | P59: THIS ROW TEMPLATE ONLY
A60: Desktop platform | B60: 4 | C60: 5 | D60: 3 | E60: 5 | F60: 3 | G60: 4 | H60: 5 | I60: 5 | J60: 4 | K60: 4 | L60: 3 | M60: 2 | N60: =AVERAGE(B60:M60) -> 3.9166667 | P60: THIS ROW TEMPLATE ONLY
A61: Customizable dashboards | B61: 4 | C61: 5 | D61: 3 | E61: 5 | F61: 5 | G61: 4 | H61: 5 | I61: 4 | J61: 3 | K61: 5 | L61: 3 | M61: 4 | N61: =AVERAGE(B61:M61) -> 4.1666667 | P61: THIS ROW TEMPLATE ONLY
A62: UX simplicity | B62: 4 | C62: 4 | D62: 4 | E62: 4 | F62: 2 | G62: 3 | H62: 3 | I62: 5 | J62: 5 | K62: 3 | L62: 5 | M62: 5 | N62: =AVERAGE(B62:M62) -> 3.9166667 | P62: THIS ROW TEMPLATE ONLY
A63: Accessibility and onboarding | B63: 5 | C63: 2 | D63: 2 | E63: 4 | F63: 3 | G63: 5 | H63: 4 | I63: 4 | J63: 5 | K63: 4 | L63: 5 | M63: 4 | N63: =AVERAGE(B63:M63) -> 3.9166667 | P63: THIS ROW TEMPLATE ONLY
A64: I. Pricing & Fees | B64: =AVERAGE(B65:B69) -> 3.2 | C64: =AVERAGE(C65:C69) -> 3.4 | D64: =AVERAGE(D65:D69) -> 4.4 | E64: =AVERAGE(E65:E69) -> 2.8 | F64: =AVERAGE(F65:F69) -> 3.8 | G64: =AVERAGE(G65:G69) -> 3.8 | H64: =AVERAGE(H65:H69) -> 3.4 | I64: =AVERAGE(I65:I69) -> 3.8 | ... M64: =AVERAGE(M65:M69) -> 3 | N64: =AVERAGE(B64:M64) -> 3.45 | P64: **The data in the rows below were AI generated and need to be verified
A65: Commissions | B65: 4 | C65: 5 | D65: 4 | E65: 4 | F65: 4 | G65: 3 | H65: 3 | I65: 4 | J65: 2 | K65: 3 | L65: 3 | M65: 3 | N65: =AVERAGE(B65:M65) -> 3.5 | P65: THIS ROW TEMPLATE ONLY
A66: Options contract fees | B66: 5 | C66: 4 | D66: 4 | E66: 2 | F66: 3 | G66: 4 | H66: 4 | I66: 3 | J66: 4 | K66: 2 | L66: 3 | M66: 4 | N66: =AVERAGE(B66:M66) -> 3.5 | P66: THIS ROW TEMPLATE ONLY
A67: Margin rates | B67: 2 | C67: 2 | D67: 4 | E67: 3 | F67: 5 | G67: 2 | H67: 4 | I67: 5 | J67: 5 | K67: 5 | L67: 4 | M67: 3 | N67: =AVERAGE(B67:M67) -> 3.6666667 | P67: THIS ROW TEMPLATE ONLY
A68: Data subscription fees | B68: 2 | C68: 4 | D68: 5 | E68: 2 | F68: 2 | G68: 5 | H68: 2 | I68: 2 | J68: 3 | K68: 3 | L68: 4 | M68: 2 | N68: =AVERAGE(B68:M68) -> 3 | P68: THIS ROW TEMPLATE ONLY
A69: Premium tiers | B69: 3 | C69: 2 | D69: 5 | E69: 3 | F69: 5 | G69: 5 | H69: 4 | I69: 5 | J69: 4 | K69: 2 | L69: 2 | M69: 3 | N69: =AVERAGE(B69:M69) -> 3.5833333 | P69: THIS ROW TEMPLATE ONLY
A70: Community & Social Features | B70: =AVERAGE(B71:B75) -> 3.4 | C70: =AVERAGE(C71:C75) -> 4 | D70: =AVERAGE(D71:D75) -> 3 | E70: =AVERAGE(E71:E75) -> 3 | F70: =AVERAGE(F71:F75) -> 3.8 | G70: =AVERAGE(G71:G75) -> 3.6 | H70: =AVERAGE(H71:H75) -> 3.2 | I70: =AVERAGE(I71:I75) -> 2.8 | ... M70: =AVERAGE(M71:M75) -> 3.4 | N70: =AVERAGE(B70:M70) -> 3.5333333 | P70: **The data in the rows below were AI generated and need to be verified
A71: Chatrooms | B71: 3 | C71: 4 | D71: 2 | E71: 3 | F71: 3 | G71: 3 | H71: 3 | I71: 2 | J71: 5 | K71: 5 | L71: 5 | M71: 4 | N71: =AVERAGE(B71:M71) -> 3.5 | P71: THIS ROW TEMPLATE ONLY
A72: Copy trading | B72: 2 | C72: 3 | D72: 4 | E72: 4 | F72: 5 | G72: 2 | H72: 4 | I72: 3 | J72: 5 | K72: 2 | L72: 3 | M72: 3 | N72: =AVERAGE(B72:M72) -> 3.3333333 | P72: THIS ROW TEMPLATE ONLY
A73: Public portfolios | B73: 4 | C73: 3 | D73: 2 | E73: 2 | F73: 3 | G73: 4 | H73: 5 | I73: 2 | J73: 5 | K73: 4 | L73: 5 | M73: 4 | N73: =AVERAGE(B73:M73) -> 3.5833333 | P73: THIS ROW TEMPLATE ONLY
A74: Social feeds | B74: 5 | C74: 5 | D74: 2 | E74: 2 | F74: 5 | G74: 4 | H74: 2 | I74: 2 | J74: 3 | K74: 2 | L74: 4 | M74: 2 | N74: =AVERAGE(B74:M74) -> 3.1666667 | P74: THIS ROW TEMPLATE ONLY
A75: Creator tools | B75: 3 | C75: 5 | D75: 5 | E75: 4 | F75: 3 | G75: 5 | H75: 2 | I75: 5 | J75: 4 | K75: 5 | L75: 4 | M75: 4 | N75: =AVERAGE(B75:M75) -> 4.0833333 | P75: THIS ROW TEMPLATE ONLY
A76: Compliance, Security & Reliability | B76: =AVERAGE(B77:B80) -> 2.25 | C76: =AVERAGE(C77:C80) -> 4.25 | D76: =AVERAGE(D77:D80) -> 3.25 | E76: =AVERAGE(E77:E80) -> 4.5 | F76: =AVERAGE(F77:F80) -> 4.25 | G76: =AVERAGE(G77:G80) -> 3 | H76: =AVERAGE(H77:H80) -> 3.5 | I76: =AVERAGE(I77:I80) -> 4.75 | ... M76: =AVERAGE(M77:M80) -> 3.5 | N76: =AVERAGE(B76:M76) -> 3.6458333 | P76: **The data in the rows below were AI generated and need to be verified
A77: SIPC/FDIC protections | B77: 2 | C77: 3 | D77: 4 | E77: 5 | F77: 5 | G77: 4 | H77: 2 | I77: 5 | J77: 2 | K77: 4 | L77: 4 | M77: 4 | N77: =AVERAGE(B77:M77) -> 3.6666667 | P77: THIS ROW TEMPLATE ONLY
A78: Encryption/MFA | B78: 2 | C78: 5 | D78: 2 | E78: 5 | F78: 5 | G78: 2 | H78: 4 | I78: 5 | J78: 5 | K78: 2 | L78: 3 | M78: 4 | N78: =AVERAGE(B78:M78) -> 3.6666667 | P78: THIS ROW TEMPLATE ONLY
A79: Outage history | B79: 3 | C79: 4 | D79: 5 | E79: 5 | F79: 2 | G79: 2 | H79: 3 | I79: 4 | J79: 2 | K79: 5 | L79: 2 | M79: 3 | N79: =AVERAGE(B79:M79) -> 3.3333333 | P79: THIS ROW TEMPLATE ONLY
A80: Execution speed | B80: 2 | C80: 5 | D80: 2 | E80: 3 | F80: 5 | G80: 4 | H80: 5 | I80: 5 | J80: 5 | K80: 3 | L80: 5 | M80: 3 | N80: =AVERAGE(B80:M80) -> 3.9166667 | P80: THIS ROW TEMPLATE ONLY
A81: Integrations & Ecosystem | B81: =AVERAGE(B82:B86) -> 4.2 | C81: =AVERAGE(C82:C86) -> 3.6 | D81: =AVERAGE(D82:D86) -> 3.8 | E81: =AVERAGE(E82:E86) -> 3.4 | F81: =AVERAGE(F82:F86) -> 3.6 | G81: =AVERAGE(G82:G86) -> 4.6 | H81: =AVERAGE(H82:H86) -> 3.8 | I81: =AVERAGE(I82:I86) -> 3.2 | ... M81: =AVERAGE(M82:M86) -> 3.6 | N81: =AVERAGE(B81:M81) -> 3.75 | P81: **The data in the rows below were AI generated and need to be verified
A82: API availability | B82: 5 | C82: 3 | D82: 3 | E82: 2 | F82: 4 | G82: 5 | H82: 4 | I82: 2 | J82: 4 | K82: 4 | L82: 5 | M82: 3 | N82: =AVERAGE(B82:M82) -> 3.6666667 | P82: THIS ROW TEMPLATE ONLY
A83: Spreadsheet plugins | B83: 5 | C83: 5 | D83: 4 | E83: 4 | F83: 5 | G83: 5 | H83: 3 | I83: 3 | J83: 5 | K83: 3 | L83: 5 | M83: 2 | N83: =AVERAGE(B83:M83) -> 4.0833333 | P83: THIS ROW TEMPLATE ONLY
A84: Brokerage integrations | B84: 4 | C84: 5 | D84: 5 | E84: 5 | F84: 3 | G84: 5 | H84: 3 | I84: 4 | J84: 2 | K84: 5 | L84: 2 | M84: 5 | N84: =AVERAGE(B84:M84) -> 4 | P84: THIS ROW TEMPLATE ONLY
A85: Third-party tools | B85: 2 | C85: 3 | D85: 5 | E85: 3 | F85: 2 | G85: 5 | H85: 4 | I85: 5 | J85: 2 | K85: 4 | L85: 5 | M85: 4 | N85: =AVERAGE(B85:M85) -> 3.6666667 | P85: THIS ROW TEMPLATE ONLY
A86: Algo connectivity | B86: 5 | C86: 2 | D86: 2 | E86: 3 | F86: 4 | G86: 3 | H86: 5 | I86: 2 | J86: 2 | K86: 5 | L86: 3 | M86: 4 | N86: =AVERAGE(B86:M86) -> 3.3333333 | P86: THIS ROW TEMPLATE ONLY
A87: Artificial Intelligence & Automation | B87: =AVERAGE(B88:B92) -> 2.8 | C87: =AVERAGE(C88:C92) -> 2.8 | D87: =AVERAGE(D88:D92) -> 3.8 | E87: =AVERAGE(E88:E92) -> 3.4 | F87: =AVERAGE(F88:F92) -> 4.2 | G87: =AVERAGE(G88:G92) -> 3.6 | H87: =AVERAGE(H88:H92) -> 4.2 | I87: =AVERAGE(I88:I92) -> 4 | ... M87: =AVERAGE(M88:M92) -> 4 | N87: =AVERAGE(B87:M87) -> 3.6333333 | P87: **The data in the rows below were AI generated and need to be verified
A88: AI market insights | B88: 2 | C88: 2 | D88: 4 | E88: 2 | F88: 4 | G88: 4 | H88: 5 | I88: 3 | J88: 3 | K88: 5 | L88: 3 | M88: 3 | N88: =AVERAGE(B88:M88) -> 3.3333333 | P88: THIS ROW TEMPLATE ONLY
A89: Personalized recommendations | B89: 3 | C89: 2 | D89: 5 | E89: 3 | F89: 5 | G89: 3 | H89: 5 | I89: 4 | J89: 5 | K89: 4 | L89: 2 | M89: 5 | N89: =AVERAGE(B89:M89) -> 3.8333333 | P89: THIS ROW TEMPLATE ONLY
A90: AI chat tools | B90: 4 | C90: 3 | D90: 2 | E90: 5 | F90: 4 | G90: 4 | H90: 4 | I90: 5 | J90: 4 | K90: 3 | L90: 5 | M90: 5 | N90: =AVERAGE(B90:M90) -> 4 | P90: THIS ROW TEMPLATE ONLY
A91: Automated portfolio optimization | B91: 2 | C91: 3 | D91: 5 | E91: 4 | F91: 4 | G91: 4 | H91: 5 | I91: 4 | J91: 2 | K91: 2 | L91: 5 | M91: 4 | N91: =AVERAGE(B91:M91) -> 3.6666667 | P91: THIS ROW TEMPLATE ONLY
A92: Fraud/risk detection | B92: 3 | C92: 4 | D92: 3 | E92: 3 | F92: 4 | G92: 3 | H92: 2 | I92: 4 | J92: 5 | K92: 2 | L92: 4 | M92: 3 | N92: =AVERAGE(B92:M92) -> 3.3333333 | P92: THIS ROW TEMPLATE ONLY
A93: News & Data Integration | B93: =AVERAGE(B94:B98) -> 4 | C93: =AVERAGE(C94:C98) -> 3.8 | D93: =AVERAGE(D94:D98) -> 4 | E93: =AVERAGE(E94:E98) -> 3.6 | F93: =AVERAGE(F94:F98) -> 3.4 | G93: =AVERAGE(G94:G98) -> 2.4 | H93: =AVERAGE(H94:H98) -> 4.6 | I93: =AVERAGE(I94:I98) -> 2.8 | ... M93: =AVERAGE(M94:M98) -> 4.2 | N93: =AVERAGE(B93:M93) -> 3.55 | P93: **The data in the rows below were AI generated and need to be verified
A94: Real-time news | B94: 2 | C94: 4 | D94: 4 | E94: 5 | F94: 3 | G94: 3 | H94: 4 | I94: 4 | J94: 3 | K94: 4 | L94: 5 | M94: 4 | N94: =AVERAGE(B94:M94) -> 3.75 | P94: THIS ROW TEMPLATE ONLY
A95: Integrated media sources | B95: 4 | C95: 2 | D95: 5 | E95: 2 | F95: 3 | G95: 3 | H95: 4 | I95: 2 | J95: 5 | K95: 2 | L95: 4 | M95: 2 | N95: =AVERAGE(B95:M95) -> 3.1666667 | P95: THIS ROW TEMPLATE ONLY
A96: Sentiment analysis | B96: 5 | C96: 4 | D96: 4 | E96: 5 | F96: 4 | G96: 2 | H96: 5 | I96: 2 | J96: 4 | K96: 3 | L96: 2 | M96: 5 | N96: =AVERAGE(B96:M96) -> 3.75 | P96: THIS ROW TEMPLATE ONLY
A97: Event-driven alerts | B97: 4 | C97: 5 | D97: 2 | E97: 3 | F97: 2 | G97: 2 | H97: 5 | I97: 2 | J97: 2 | K97: 3 | L97: 3 | M97: 5 | N97: =AVERAGE(B97:M97) -> 3.1666667 | P97: THIS ROW TEMPLATE ONLY
A98: Customization & filtering | B98: 5 | C98: 4 | D98: 5 | E98: 3 | F98: 5 | G98: 2 | H98: 5 | I98: 4 | J98: 2 | K98: 4 | L98: 3 | M98: 5 | N98: =AVERAGE(B98:M98) -> 3.9166667 | P98: THIS ROW TEMPLATE ONLY
A99: Average | B99: =AVERAGE(B9:B98) -> 3.2966991 | C99: =AVERAGE(C9:C98) -> 3.3372213 | D99: =AVERAGE(D9:D98) -> 3.5351882 | E99: =AVERAGE(E9:E98) -> 3.3750812 | F99: =AVERAGE(F9:F98) -> 3.3086856 | G99: =AVERAGE(G9:G98) -> 3.3901908 | H99: =AVERAGE(H9:H98) -> 3.4734037 | I99: =AVERAGE(I9:I98) -> 3.5755217 | ... M99: =AVERAGE(M9:M98) -> 3.4021045 | N99: =AVERAGE(B99:M99) -> 3.4399885 | P99: THIS ROW TEMPLATE ONLY

Sheet Learning Dashboard
A1: Learning, Training & Simulation | B1: =Matrix!B3 -> Bloomberg | C1: =Matrix!C3 -> Robinhood | D1: =Matrix!D3 -> Fidelity | E1: =Matrix!E3 -> Investopedia Sim | F1: =Matrix!F3 -> TradingView | G1: =Matrix!G3 -> Ally Invest | H1: =Matrix!H3 -> Empower | I1: =Matrix!I3 -> Charles Schwab | ... M1: =Matrix!M3 -> Webull
A2: Entry level learning content | B2: =Matrix!B15 -> 1 | C2: =Matrix!C15 -> 5 | D2: =Matrix!D15 -> 5 | E2: =Matrix!E15 -> 5 | F2: =Matrix!F15 -> 1 | G2: =Matrix!G15 -> 4 | H2: =Matrix!H15 -> 3 | I2: =Matrix!I15 -> 4 | ... M2: =Matrix!M15 -> 5 | P2: Takeaways
A3: Advanced Training | B3: =Matrix!B16 -> 1 | C3: =Matrix!C16 -> 3 | D3: =Matrix!D16 -> 3 | E3: =Matrix!E16 -> 2 | F3: =Matrix!F16 -> 1 | G3: =Matrix!G16 -> 3 | H3: =Matrix!H16 -> 1 | I3: =Matrix!I16 -> 4 | ... M3: =Matrix!M16 -> 5 | P3: Even platforms with the highest cumulative score lack in some areas
A4: Paper trading Sim | B4: =Matrix!B17 -> 4 | C4: =Matrix!C17 -> 4 | D4: =Matrix!D17 -> 3 | E4: =Matrix!E17 -> 3 | F4: =Matrix!F17 -> 2 | G4: =Matrix!G17 -> 3 | H4: =Matrix!H17 -> 3 | I4: =Matrix!I17 -> 3 | ... M4: =Matrix!M17 -> 4 | Q4: Guided Trading
A5: Tutorials | B5: =Matrix!B18 -> 5 | C5: =Matrix!C18 -> 2 | D5: =Matrix!D18 -> 3 | E5: =Matrix!E18 -> 3 | F5: =Matrix!F18 -> 3 | G5: =Matrix!G18 -> 3 | H5: =Matrix!H18 -> 2 | I5: =Matrix!I18 -> 3 | ... M5: =Matrix!M18 -> 2
A6: Quizzes | B6: =Matrix!B19 -> 5 | C6: =Matrix!C19 -> 3 | D6: =Matrix!D19 -> 3 | E6: =Matrix!E19 -> 5 | F6: =Matrix!F19 -> 1 | G6: =Matrix!G19 -> 4 | H6: =Matrix!H19 -> 3 | I6: =Matrix!I19 -> 4 | ... M6: =Matrix!M19 -> 1
A7: Software Training | B7: =Matrix!B20 -> 4 | C7: =Matrix!C20 -> 3 | D7: =Matrix!D20 -> 4 | E7: =Matrix!E20 -> 3 | F7: =Matrix!F20 -> 4 | G7: =Matrix!G20 -> 3 | H7: =Matrix!H20 -> 3 | I7: =Matrix!I20 -> 4 | ... M7: =Matrix!M20 -> 3
A8: Guided trade features | B8: =Matrix!B21 -> 2 | C8: =Matrix!C21 -> 2 | D8: =Matrix!D21 -> 3 | E8: =Matrix!E21 -> 2 | F8: =Matrix!F21 -> 2 | G8: =Matrix!G21 -> 3 | H8: =Matrix!H21 -> 2 | I8: =Matrix!I21 -> 5 | ... M8: =Matrix!M21 -> 2
A9: Total | B9: =SUM(B2:B8) -> 22 | C9: =SUM(C2:C8) -> 22 | D9: =SUM(D2:D8) -> 24 | E9: =SUM(E2:E8) -> 23 | F9: =SUM(F2:F8) -> 14 | G9: =SUM(G2:G8) -> 23 | H9: =SUM(H2:H8) -> 17 | I9: =SUM(I2:I8) -> 27 | ... M9: =SUM(M2:M8) -> 22 | O9: 1=Absent | P9: 2=Minimal | Q9: 3=Basic | R9: 4=Strong | S9: 5=Best In Class
